sphinx_tamer/__init__.py
sphinx_tamer/_version.py
sphinx_tamer/sentence_scan.py
sphinx_tamer/sentences.py
sphinx_tamer/sphinx_wrapper.py
sphinx_tamer/text.py
sphinx_tamer-0.2.0.dist-info/METADATA
sphinx_tamer-0.2.0.dist-info/WHEEL
sphinx_tamer-0.2.0.dist-info/entry_points.txt
sphinx_tamer-0.2.0.dist-info/licenses/LICENSE
sphinx_tamer-0.2.0.dist-info/RECORD
