Metadata-Version: 2.4
Name: sphinx_tamer
Version: 0.2.0
Summary: Python library for easy parsing of Sphinx documentation 
Project-URL: Homepage, https://github.com/DLu/sphinx_tamer
Project-URL: Bug Tracker, https://github.com/DLu/sphinx_tamer/issues
Author-email: "David V. Lu!!" <davidvlu@gmail.com>
Maintainer-email: "David V. Lu!!" <davidvlu@gmail.com>
License-File: LICENSE
Requires-Python: >=3.9
Requires-Dist: click
Requires-Dist: docutils
Requires-Dist: pyyaml
Requires-Dist: sphinx
Provides-Extra: test
Requires-Dist: pytest-cov>=2; extra == 'test'
Requires-Dist: pytest>=4; extra == 'test'
